pepperpy/__init__.py
pepperpy/cli/__init__.py
pepperpy/cli/command.py
pepperpy/cli/exceptions.py
pepperpy/cli/help.py
pepperpy/cli/keyboard.py
pepperpy/cli/parser.py
pepperpy/theme.py
pepperpy/themes/css/base.css
pepperpy/themes/css/styles.css
pepperpy/themes/yaml/dracula.yaml
pepperpy/themes/yaml/high_contrast.yaml
pepperpy/themes/yaml/light.yaml
pepperpy/themes/yaml/test.yaml
pepperpy/tui/__init__.py
pepperpy/tui/app.py
pepperpy/tui/commands.py
pepperpy/tui/events.py
pepperpy/tui/forms.py
pepperpy/tui/help.py
pepperpy/tui/keyboard.py
pepperpy/tui/screens/__init__.py
pepperpy/tui/screens/base.py
pepperpy/tui/screens/exceptions.py
pepperpy/tui/screens/loading.py
pepperpy/tui/screens.py
pepperpy/tui/theme.py
pepperpy/tui/widgets/__init__.py
pepperpy/tui/widgets/accordion.py
pepperpy/tui/widgets/base.py
pepperpy/tui/widgets/breadcrumbs.py
pepperpy/tui/widgets/card.py
pepperpy/tui/widgets/containers.py
pepperpy/tui/widgets/dialog.py
pepperpy/tui/widgets/dropdown.py
pepperpy/tui/widgets/form.py
pepperpy/tui/widgets/input.py
pepperpy/tui/widgets/navigation.py
pepperpy/tui/widgets/notification.py
pepperpy/tui/widgets/progress.py
pepperpy/tui/widgets/search_bar.py
pepperpy/tui/widgets/table.py
pepperpy/tui/widgets/tabs.py
pepperpy/tui/widgets/tooltip.py
pepperpy/tui/widgets/tree_view.py
pepperpy_console-0.3.1.dist-info/LICENSE
pepperpy_console-0.3.1.dist-info/METADATA
pepperpy_console-0.3.1.dist-info/WHEEL
pepperpy_console-0.3.1.dist-info/RECORD
