Metadata-Version: 2.3
Name: pepperpy-console
Version: 0.3.1
Summary: PepperPy console package
Author: Felipe Pimentel
Author-email: fpimentel88@gmail.com
Requires-Python: >=3.12,<4.0
Classifier: Programming Language :: Python :: 3
Classifier: Programming Language :: Python :: 3.12
Classifier: Programming Language :: Python :: 3.13
Requires-Dist: pepperpy-core[type-stubs]
Requires-Dist: rich (>=13.9.4,<14.0.0)
Requires-Dist: textual (>=1.0.0,<2.0.0)
